Workbook

Sheet DATOS
A2: Sección | B2: Descripción | C2: Tasa MRC | D2: Tasa TRO | E2: Tasa TRO - Sublimite | F2: Deducible | G2: PLAN | H2: COSTO MINIMO | I2: Moneda | J2: Cobertura
A4: Sección I | B4: Incendio de edificio, hasta la suma de | C4: 1 | D4: 2 | E4: 2 | F4: Sin deducible | G4: TAJY PREMIUM | H4: 3190000 | I4: Gs. | J4: LAP
A5: Sub-limite | B5: Incendio Contenido, hasta la suma de | C5: 2 | D5: 3 | E5: 3 | F5: 10% en todo y cada siniestro, mínimo Gs. 500.000 | G5: TAJY SUPERIOR | H5: 2695000 | I5: Uds. | J5: CAP
B6: Incendio mobiliarios y equipos, hasta la suma de | C6: 0.65 | D6: 3 | E6: 3 | F6: 10% en todo y cada siniestro, mínimo Gs. 800.000 | G6: TAJY FUERTE | H6: 2365000 | J6: CTR
B7: Robo contenido, hasta la suma de | C7: 8 | D7: 12 | E7: 5 | F7: 10% en todo y cada siniestro, mínimo Gs. 1.000.000 | G7: TAJY NOBLE | H7: 1661000
B8: Cristales, hasta la suma de | C8: 8 | D8: 12 | E8: 5 | F8: 10% en todo y cada siniestro, mínimo Gs. 1.200.000 | G8: TAJY BASICO
B9: Valores en tránsito, hasta la suma de | C9: 10 | D9: 18 | E9: 8 | F9: 10% en todo y cada siniestro, mínimo Gs. 1.500.000 | G9: MTC Y TRO | H9: 450000
B10: Valores en caja fuerte, hasta la suma de Limite maximo para valores en Ventanilla hasta el 30% del valor en Caja Fuerte | C10: 10 | D10: 15 | E10: 8 | G10: TAJY BASICO - AUTOMOVIL | H10: 600000
B11: Resp. Civil, hasta la suma de | C11: 10 | D11: 12 | E11: 8 | G11: TAJY BASICO - CAMION | H11: 1000000
B12: Equipos electronicos, hasta la suma de | C12: 15 | D12: 15 | E12: 8 | G12: TAJY BASICO - ACOPLADO | H12: 800000
B13: Sub-limite de cobertura para daños o perdidas como consecuencia de riesgos cubierto, a primer riesgo absoluto para:
B14: Daños a murrallas, cercados perimetrales y rejas, hasta la suma maxima de | C14: 22
B15: Daños por granizos, hasta la suma maximas de | C15: 22
B16: Daños por agua, hasta la suma maxima de | C16: 22
B17: Daños a los Equipos Electronicos, hasta la suma maxima de | C17: 16
B20: Tipo de Riesgos | C20: Tasa Edificio | D20: Tasa Contenido | E20: CATEGORIA
B21: VIVIENDA | C21: 0.9 | D21: =C21*60%+C21 -> 1.44 | E21: CATEGORIA A | G21: =INCENDIO!B11 -> NEGOCIO - VIVIENDA
B22: BAZAR | C22: 1.2 | D22: =C22*60%+C22 -> 1.92 | E22: CATEGORIA B | F22: Incendio de edificio, hasta la suma de | G22: =VLOOKUP(G21,$B$21:$D$69,2,0) -> 1.8
B23: BOCA DE COBRANZAS | C23: 1.2 | D23: =C23*60%+C23 -> 1.92 | E23: CATEGORIA B | F23: Incendio Contenido, hasta la suma de | G23: =VLOOKUP(G21,$B$21:$D$69,3,0) -> 2.88
B24: BOUTIQUE | C24: 1.2 | D24: =C24*60%+C24 -> 1.92 | E24: CATEGORIA B
B25: CONSULTORIO | C25: 1.2 | D25: =C25*60%+C25 -> 1.92 | E25: CATEGORIA B
B26: DESPENSA | C26: 1.2 | D26: =C26*60%+C26 -> 1.92 | E26: CATEGORIA B
B27: BODEGA | C27: 1.2 | D27: =C27*60%+C27 -> 1.92 | E27: CATEGORIA B
B28: FARMACIA | C28: 1.2 | D28: =C28*60%+C28 -> 1.92 | E28: CATEGORIA B
B29: OFICINA ADMINISTRATIVA | C29: 1.2 | D29: =C29*60%+C29 -> 1.92 | E29: CATEGORIA B
B30: LIBRERIA | C30: 1.2 | D30: =C30*60%+C30 -> 1.92 | E30: CATEGORIA B
B31: PELUQUERIA | C31: 1.2 | D31: =C31*60%+C31 -> 1.92 | E31: CATEGORIA B
B32: VENTA DE COSMETICOS | C32: 1.2 | D32: =C32*60%+C32 -> 1.92 | E32: CATEGORIA B
B33: VENTA DE ELECTRODOMESTICOS Y/O EQUIPOS ELECTRONICOS | C33: 1.2 | D33: =C33*60%+C33 -> 1.92 | E33: CATEGORIA B
B34: VENTA DE PRENDAS DE VESTIR | C34: 1.5 | D34: =C34*60%+C34 -> 2.4 | E34: CATEGORIA C
B35: VENTA DE REPUESTOS | C35: 1.5 | D35: =C35*60%+C35 -> 2.4 | E35: CATEGORIA C
... B69: GRANJA EN GENERAL | C69: 3.5 | D69: =C69*60%+C69 -> 5.6 | E69: CATEGORIA I
A71: Tipos de transporte | B71: Cobertura
A73: Transporte de Ganado | B73: Transporte de Mercaderia
A74: Transporte de Mercaderias Varias | B74: LIBRE AVERIA PARTICULAR | C74: 1.2
A75: Transporte de Carne | B75: CON AVERIA PARTICULAR | C75: 2
A76: Transporte de | B76: CONTRA TODO RIESGOS | C76: 4.5

Sheet TIPOS DE RIESGOS
A1: Grupo A - Multirriesgo Comercio | B1: Grupo B - Todo Riesgo Operativo
A2: BAZAR | B2: AGROVETERINARIA
A3: BOCA DE COBRANZAS | B3: AUTOSERVICE
A4: BOUTIQUE | B4: CANCHA SINTÉTICA
A5: CONSULTORIO | B5: CASA DE EQUIPAMIENTOS
A6: DESPENSA | B6: CENTRO LUBRICACION
A7: BODEGA | B7: CENTRO MATERNAL Y ESCUELA HOGAR
A8: FARMACIA | B8: COMPLEJO SOCIAL
A9: INMOBILIARIA | B9: CONFECCION DE PRENDAS DE VESTIR
A10: LIBRERIA | B10: COOPERATIVA
A11: OFICINA ADMINISTRATIVA | B11: DEPOSITO
A12: PELUQUERIA | B12: ESTACION DE SERVICIO Y SHOP
... A20: ENTRE OTROS LOCALES SIN PROCESO | B20: MINIMERCADO
B21: MOTEL
B22: MUNICIPALIDAD
B23: NEGOCIO - VIVIENDA
B24: PIZZERIA
B25: SANTUARIO
B26: SUPERMERCADO
B27: TALLER DE MAQUINAS
B28: TALLER MECANICO
B29: TINGLADOS
B30: PANADERIAS
B31: DEPOSITOS
B32: INDUSTRIAS
B33: ENTRE OTROS LOCALES QUE POSEA PROCESO

Sheet Requisitos Minimos
A1: Anexo 1 - Documentos Mínimos Requeridos
A3: Nuevos
A4: ü Cedula de Identidad vigente ambos lados
A5: ü Cedula Tributaria (en caso que lo amerite)
A6: ü Factura de servicios básicos donde se visualice la Cta. Ctral. (ANDE, ESSAP) (en caso que lo amerite)
A7: ü Tasación (en caso que lo amerite)
A8: ü Propuesta de seguros
A9: ü Inspeccion de Riesgo (en caso que lo amerite)
A11: Renovación
A12: ü Propuesta de seguros
A13: ü Cedula de Identidad vigente ambos lados
A14: Consideraciones Generales
... A16: ü El Riesgo tendrá cobertura cuando la propuesta sea aceptada por el asegurador, en el área técnica

Sheet INCENDIO
F10: Calculo Auxiliar
A11: Riesgo | B11: NEGOCIO - VIVIENDA
A12: Categoria | B12: =VLOOKUP(B11,DATOS!$B$21:$E$69,4,0) -> CATEGORIA E
A13: Sección | B13: Descripción | C13: Moneda | D13: Suma asegurada | E13: Deducible | F13: Ubicación | G13: Tasa | H13: Costo | I13: LIMITE HASTA Gs. 500.000.000 en edificio y contenido
A14: Sección I | B14: Incendio de edificio, hasta la suma de | C14: Gs. | D14: 50000000 | E14: Sin deducible | G14: =IFERROR(VLOOKUP(B14,DATOS!$F$22:$G$23,2,0)," ") -> 1.8 | H14: =IFERROR(D14*G14/1000," ") -> 90000
A15: Sección I | B15: Incendio Contenido, hasta la suma de | C15: Gs. | D15: 100000000 | E15: Sin deducible | G15: =IFERROR(VLOOKUP(B15,DATOS!$F$22:$G$23,2,0)," ") -> 2.88 | H15: =IFERROR(D15*G15/1000," ") -> 288000
G16: =IFERROR(VLOOKUP(B16,DATOS!$F$22:$G$23,2,0)," ")
G17: =IFERROR(VLOOKUP(B17,DATOS!$F$22:$G$23,2,0)," ")
G18: =IFERROR(VLOOKUP(B18,DATOS!$F$22:$G$23,2,0)," ")
G19: =IFERROR(VLOOKUP(B19,DATOS!$F$22:$G$23,2,0)," ")
G20: =IFERROR(VLOOKUP(B20,DATOS!$F$22:$G$23,2,0)," ")
G21: =IFERROR(VLOOKUP(B21,DATOS!$F$22:$G$23,2,0)," ")
G22: =IFERROR(VLOOKUP(B22,DATOS!$F$22:$G$23,2,0)," ")
G23: =IFERROR(VLOOKUP(B23,DATOS!$F$22:$G$23,2,0)," ")
G24: =IFERROR(VLOOKUP(B24,DATOS!$F$22:$G$23,2,0)," ")
G25: =IFERROR(VLOOKUP(B25,DATOS!$F$22:$G$23,2,0)," ")
G26: =IFERROR(VLOOKUP(B26,DATOS!$F$22:$G$23,2,0)," ")
G27: =IFERROR(VLOOKUP(B27,DATOS!$F$22:$G$23,2,0)," ")
... G31: =IFERROR(VLOOKUP(B31,DATOS!$F$22:$G$23,2,0)," ")
G32: =IFERROR(VLOOKUP(B32,DATOS!$F$22:$G$23,2,0)," ") | H32: =IFERROR(D32*G32/1000," ")
G33: =IFERROR(VLOOKUP(B33,DATOS!$F$22:$G$23,2,0)," ")
B34: Suma total Gs. | D34: =SUM(D14:D32) -> 150000000 | G34: =H34/D34*1000 -> 3 | H34: =IF(SUM(H14:H32)<=DATOS!$H$9,DATOS!$H$9,(SUM(H14:H32))) -> 450000
B35: Costo Contado Gs. | D35: =H34 -> 450000
B36: Costo financiado de Inicial y 11 Cuotas de Gs. | D36: =ROUNDUP(D35*1.1/12,-3) -> 42000

Sheet TM
E10: Calculo Auxiliar
A11: Tipo de Mercaderia: | B11: Electrodomesticos en Gral.
A12: Cobertura | B12: Descripción | C12: Moneda | D12: Suma asegurada | E12: Deducible | F12: Tasa | G12: Costo
A13: CONTRA TODO RIESGOS | B13: =CONCATENATE(DATOS!B73," ",B11) -> Transporte de Mercaderia Electrodomesticos en Gral. | C13: Gs. | D13: 100000000 | E13: 10% en todo y cada siniestro, mínimo Gs. 500.000 | F13: =IFERROR(VLOOKUP(A13,DATOS!$B$74:$C$76,2,0)," ") -> 4.5 | G13: =IFERROR(D13*F13/100," ") -> 4500000
B14: Suma total Gs. | D14: =SUM(D13:D13) -> 100000000 | F14: =G14/D14*100 -> 4.5 | G14: =IF(SUM(G13:G13)<=DATOS!$H$9,DATOS!$H$9,(SUM(G13:G13))) -> 4500000
B15: Costo Contado Gs. | D15: =G14 -> 4500000
B16: Costo financiado de Inicial y 11 Cuotas de Gs. | D16: =ROUNDUP(D15*1.1/12,-3) -> 413000

Sheet MRC
A11: Riesgo | B11: BAZAR | E11: Calculo Auxiliar
A12: Ubicación
A13: Tasa Global | B13: =F26 -> 3.9659794
A14: Sección | B14: Descripción | C14: Moneda | D14: Suma asegurada | E14: Deducible | F14: Tasa | G14: Costo | I14: LIMITE HASTA Gs. 850.000.000 en edificio y contenido
A15: Sección I | B15: Incendio de edificio, hasta la suma de | C15: Gs. | D15: 200000000 | E15: Sin deducible | F15: =IFERROR(VLOOKUP(B15,DATOS!$B$4:$D$17,2,0)," ") -> 1 | G15: =IFERROR(D15*F15/1000," ") -> 200000
A16: Sección I | B16: Incendio Contenido, hasta la suma de | C16: Gs. | D16: 500000000 | E16: Sin deducible | F16: =IFERROR(VLOOKUP(B16,DATOS!$B$4:$D$17,2,0)," ") -> 2 | G16: =IFERROR(D16*F16/1000," ") -> 1000000
A17: Sección I | B17: Robo contenido, hasta la suma de | C17: Gs. | D17: 50000000 | E17: 10% en todo y cada siniestro, mínimo Gs. 500.000 | F17: =IFERROR(VLOOKUP(B17,DATOS!$B$4:$D$17,2,0)," ") -> 8 | G17: =IFERROR(D17*F17/1000," ") -> 400000
A18: Sección I | B18: Cristales, hasta la suma de | C18: Gs. | D18: 100000000 | E18: 10% en todo y cada siniestro, mínimo Gs. 500.000 | F18: =IFERROR(VLOOKUP(B18,DATOS!$B$4:$D$17,2,0)," ") -> 8 | G18: =IFERROR(D18*F18/1000," ") -> 800000
A19: Sección I | B19: Robo contenido, hasta la suma de | C19: Gs. | D19: 10000000 | E19: 10% en todo y cada siniestro, mínimo Gs. 500.000 | F19: =IFERROR(VLOOKUP(B19,DATOS!$B$4:$D$17,2,0)," ") -> 8 | G19: =IFERROR(D19*F19/1000," ") -> 80000
A20: Sección I | B20: Valores en caja fuerte, hasta la suma de Limite maximo para valores en Ventanilla hasta el 30% del valor en Caja Fuerte | C20: Gs. | D20: 10000000 | E20: 10% en todo y cada siniestro, mínimo Gs. 500.000 | F20: =IFERROR(VLOOKUP(B20,DATOS!$B$4:$D$17,2,0)," ") -> 10 | G20: =IFERROR(D20*F20/1000," ") -> 100000
A21: Sección I | B21: Resp. Civil, hasta la suma de | C21: Gs. | D21: 100000000 | E21: 10% en todo y cada siniestro, mínimo Gs. 500.000 | F21: =IFERROR(VLOOKUP(B21,DATOS!$B$4:$D$17,2,0)," ") -> 10 | G21: =IFERROR(D21*F21/1000," ") -> 1000000
A22: Sub-limite | B22: Daños a murrallas, cercados perimetrales y rejas, hasta la suma maxima de | C22: Gs. | D22: 1000000 | E22: 10% en todo y cada siniestro, mínimo Gs. 500.000 | F22: =IFERROR(VLOOKUP(B22,DATOS!$B$4:$D$17,2,0)," ") -> 22 | G22: =IFERROR(D22*F22/1000," ") -> 22000
A23: Sub-limite | B23: Daños por granizos, hasta la suma maximas de | C23: Gs. | D23: 5000000 | E23: 10% en todo y cada siniestro, mínimo Gs. 500.000 | F23: =IFERROR(VLOOKUP(B23,DATOS!$B$4:$D$17,2,0)," ") -> 22 | G23: =IFERROR(D23*F23/1000," ") -> 110000
A24: Sub-limite | B24: Daños por agua, hasta la suma maxima de | C24: Gs. | D24: 2500000 | E24: 10% en todo y cada siniestro, mínimo Gs. 500.000 | F24: =IFERROR(VLOOKUP(B24,DATOS!$B$4:$D$17,2,0)," ") -> 22 | G24: =IFERROR(D24*F24/1000," ") -> 55000
A25: Sub-limite | B25: Daños a los Equipos Electronicos, hasta la suma maxima de | C25: Gs. | D25: 5000000 | E25: 10% en todo y cada siniestro, mínimo Gs. 500.000 | F25: =IFERROR(VLOOKUP(B25,DATOS!$B$4:$D$17,2,0)," ") -> 16 | G25: =IFERROR(D25*F25/1000," ") -> 80000
B26: Suma total Gs. | D26: =SUM(D15:D21) -> 970000000 | F26: =G26/D26*1000 -> 3.9659794 | G26: =IF(SUM(G15:G25)<=DATOS!$H$9,DATOS!$H$9,(SUM(G15:G25))) -> 3847000
B27: Costo Contado Gs. | D27: =G26 -> 3847000
B28: Costo financiado de Inicial y 11 Cuotas de Gs. | D28: =ROUNDUP(D27*1.1/12,-3) -> 353000

Sheet TRO
E10: Calculo Auxiliar
A11: Riesgo | B11: DEPOSITO
A12: Ubicación
A13: Tasa Global | B13: =F24 -> 4.4454545
A14: Sección | B14: Descripción | C14: Moneda | D14: Suma asegurada | E14: Deducible | F14: Tasa | G14: Costo | H14: LIMITE HASTA Gs. 850.000.000 en edificio y contenido
A15: Sección I | B15: Incendio de edificio, hasta la suma de | C15: Gs. | D15: 200000000 | E15: Sin deducible | F15: =IFERROR(VLOOKUP(B15,DATOS!$B$4:$E$12,4,0)," ") -> 2 | G15: =IFERROR(D15*F15/1000," ") -> 400000
A16: Sección I | B16: Incendio Contenido, hasta la suma de | C16: Gs. | D16: 500000000 | E16: Sin deducible | F16: =IFERROR(VLOOKUP(B16,DATOS!$B$4:$E$12,4,0)," ") -> 3 | G16: =IFERROR(D16*F16/1000," ") -> 1500000
A17: Sub-limite | B17: Robo contenido, hasta la suma de | C17: Gs. | D17: 50000000 | E17: 10% en todo y cada siniestro, mínimo Gs. 500.000 | F17: =IFERROR(VLOOKUP(B17,DATOS!$B$4:$E$12,4,0)," ") -> 5 | G17: =IFERROR(D17*F17/1000," ") -> 250000
A18: Sub-limite | B18: Cristales, hasta la suma de | C18: Gs. | D18: 20000000 | E18: 10% en todo y cada siniestro, mínimo Gs. 500.000 | F18: =IFERROR(VLOOKUP(B18,DATOS!$B$4:$E$12,4,0)," ") -> 5 | G18: =IFERROR(D18*F18/1000," ") -> 100000
A19: Sub-limite | B19: Valores en tránsito, hasta la suma de | C19: Gs. | D19: 50000000 | E19: 10% en todo y cada siniestro, mínimo Gs. 500.000 | F19: =IFERROR(VLOOKUP(B19,DATOS!$B$4:$E$12,4,0)," ") -> 8 | G19: =IFERROR(D19*F19/1000," ") -> 400000
A20: Sub-limite | B20: Valores en caja fuerte, hasta la suma de Limite maximo para valores en Ventanilla hasta el 30% del valor en Caja Fuerte | C20: Gs. | D20: 30000000 | E20: 10% en todo y cada siniestro, mínimo Gs. 500.000 | F20: =IFERROR(VLOOKUP(B20,DATOS!$B$4:$E$12,4,0)," ") -> 8 | G20: =IFERROR(D20*F20/1000," ") -> 240000
A21: Sub-limite | B21: Resp. Civil, hasta la suma de | C21: Gs. | D21: 100000000 | E21: 10% en todo y cada siniestro, mínimo Gs. 500.000 | F21: =IFERROR(VLOOKUP(B21,DATOS!$B$4:$E$12,4,0)," ") -> 8 | G21: =IFERROR(D21*F21/1000," ") -> 800000
A22: Sub-limite | B22: Equipos electronicos, hasta la suma de | D22: 150000000 | E22: 10% en todo y cada siniestro, mínimo Gs. 500.000 | F22: =IFERROR(VLOOKUP(B22,DATOS!$B$4:$E$12,4,0)," ") -> 8 | G22: =IFERROR(D22*F22/1000," ") -> 1200000
B23: Suma total Gs. | D23: =SUM(D15:D16) -> 700000000 | F23: =IFERROR(VLOOKUP(B23,DATOS!$B$4:$E$12,4,0)," ") | G23: =SUM(D15:D22) -> 1100000000
B24: Costo Contado Gs. | D24: =G24 -> 4890000 | F24: =G24/G23*1000 -> 4.4454545 | G24: =IF(SUM(G15:G22)<=DATOS!$H$9,DATOS!$H$9,(SUM(G15:G22))) -> 4890000
B25: Costo financiado de Inicial y 11 Cuotas de Gs. | D25: =ROUNDUP(D24*1.1/12,-3) -> 449000
A27: Riesgo | B27: DEPOSITO
A28: Ubicación
A29: Tasa Global | B29: =F39 -> 8.3846154
A30: Sección | B30: Descripción | C30: Moneda | D30: Suma asegurada | E30: Deducible | F30: Tasa | G30: Costo
A31: Sección I | B31: Incendio de edificio, hasta la suma de | C31: Gs. | D31: 200000000 | E31: Sin deducible | F31: =IFERROR(VLOOKUP(B31,DATOS!$B$4:$E$12,3,0)," ") -> 2 | G31: =IFERROR(D31*F31/1000," ") -> 400000
A32: Sección I | B32: Incendio Contenido, hasta la suma de | C32: Gs. | D32: 500000000 | E32: Sin deducible | F32: =IFERROR(VLOOKUP(B32,DATOS!$B$4:$E$12,3,0)," ") -> 3 | G32: =IFERROR(D32*F32/1000," ") -> 1500000
A33: Sección I | B33: Robo contenido, hasta la suma de | C33: Gs. | D33: 50000000 | E33: 10% en todo y cada siniestro, mínimo Gs. 500.000 | F33: =IFERROR(VLOOKUP(B33,DATOS!$B$4:$E$12,3,0)," ") -> 12 | G33: =IFERROR(D33*F33/1000," ") -> 600000
A34: Sección I | B34: Cristales, hasta la suma de | C34: Gs. | D34: 100000000 | E34: 10% en todo y cada siniestro, mínimo Gs. 500.000 | F34: =IFERROR(VLOOKUP(B34,DATOS!$B$4:$E$12,3,0)," ") -> 12 | G34: =IFERROR(D34*F34/1000," ") -> 1200000
A35: Sección I | B35: Valores en tránsito, hasta la suma de | C35: Gs. | D35: 250000000 | E35: 10% en todo y cada siniestro, mínimo Gs. 500.000 | F35: =IFERROR(VLOOKUP(B35,DATOS!$B$4:$E$12,3,0)," ") -> 18 | G35: =IFERROR(D35*F35/1000," ") -> 4500000
A36: Sección I | B36: Valores en caja fuerte, hasta la suma de Limite maximo para valores en Ventanilla hasta el 30% del valor en Caja Fuerte | C36: Gs. | D36: 100000000 | E36: 10% en todo y cada siniestro, mínimo Gs. 500.000 | F36: =IFERROR(VLOOKUP(B36,DATOS!$B$4:$E$12,3,0)," ") -> 15 | G36: =IFERROR(D36*F36/1000," ") -> 1500000
A37: Sección I | B37: Resp. Civil, hasta la suma de | C37: Gs. | D37: 100000000 | E37: 10% en todo y cada siniestro, mínimo Gs. 500.000 | F37: =IFERROR(VLOOKUP(B37,DATOS!$B$4:$E$12,3,0)," ") -> 12 | G37: =IFERROR(D37*F37/1000," ") -> 1200000
A38: Sección I | B38: Equipos electronicos, hasta la suma de | C38: Gs. | D38: 100000000 | E38: 10% en todo y cada siniestro, mínimo Gs. 500.000 | F38: =IFERROR(VLOOKUP(B38,DATOS!$B$4:$E$12,3,0)," ") -> 15 | G38: =IFERROR(D38*F38/1000," ") -> 1500000
B39: Suma total Gs. | D39: =SUM(D31:D37) -> 1300000000 | F39: =G39/D39*1000 -> 8.3846154 | G39: =IF(SUM(G30:G37)<=DATOS!$H$9,DATOS!$H$9,(SUM(G30:G37))) -> 10900000
B40: Costo Contado Gs. | D40: =G39 -> 10900000
B41: Costo financiado de Inicial y 11 Cuotas de Gs. | D41: =ROUNDUP(D40*1.1/12,-3) -> 1000000

Sheet AUTO - FLOTA
A9: Descuento | B9: 0.15 | H9: Calculo Auxiliar
A10: Descuento Total | B10: =B9+10% -> 0.25 | J10: CALCULO AUXILIAR
A11: Tipo de Moneda | B11: Gs.
A12: Cambio del Moneda | B12: 7800
A13: ITEM | B13: MARCA | C13: MODELO | D13: AÑO | E13: CAPITAL VEHICULO ASEGURADO GS. | F13: CAPITAL VEHICULO ASEGURADO USD. | G13: Costo Minimo | H13: PLAN | I13: CODIGO | J13: TDR | K13: TCD | L13: CA | M13: CA | N13: Minimo | O13: PLAN | P13: CODIGO
A14: 1 | B14: TOYOTA | C14: SIENTA | D14: 2004 | E14: 100000000 | F14: =E14/$B$12 -> 12820.513 | G14: =VLOOKUP(H14,DATOS!$G$4:$H$12,2,0) -> 3190000 | H14: TAJY PREMIUM | I14: =IFERROR(VLOOKUP(H14,$O$14:$P$17,2,0)," ") -> 4 | J14: =IFERROR(VLOOKUP(E14,[1]Hoja1!$A$4:$J$354,I14,1)," ") -> 6.2506332 | K14: =IFERROR(-J14*$B$9+J14," ") -> 5.3130382 | L14: =IF(H14=$O$18,G14,IF(H14=O19,G14,IF(H14=O20,G14,IFERROR(IF(E14*K14/100<=$G$14,$G$14,E14*K14/100)," ")))) -> 5313038.2 | M14: =L14/$B$12 -> 681.15874 | O14: TAJY PREMIUM | P14: 4
A15: 2 | B15: JAC | C15: HF1028H | D15: 2016 | E15: 200000000 | F15: =E15/$B$12 -> 25641.026 | G15: =VLOOKUP(H15,DATOS!$G$4:$H$12,2,0) -> 3190000 | H15: TAJY PREMIUM | I15: =IFERROR(VLOOKUP(H15,$O$14:$P$17,2,0)," ") -> 4 | J15: =IFERROR(VLOOKUP(E15,[1]Hoja1!$A$4:$J$354,I15,1)," ") -> 4.2030405 | K15: =IFERROR(-J15*$B$9+J15," ") -> 3.5725844 | L15: =IF(H15=$O$18,G15,IF(H15=O20,G15,IF(H15=O21,G15,IFERROR(IF(E15*K15/100<=$G$14,$G$14,E15*K15/100)," ")))) -> 7145168.8 | M15: =L15/$B$12 -> 916.04728 | O15: TAJY SUPERIOR | P15: 6
A16: 3 | B16: TOYOTA | C16: NOAH | D16: 2004 | E16: 450000000 | F16: =E16/$B$12 -> 57692.308 | G16: =VLOOKUP(H16,DATOS!$G$4:$H$12,2,0) -> 3190000 | H16: TAJY PREMIUM | I16: =IFERROR(VLOOKUP(H16,$O$14:$P$17,2,0)," ") -> 4 | J16: =IFERROR(VLOOKUP(E16,[1]Hoja1!$A$4:$J$354,I16,1)," ") -> 4.0150013 | K16: =IFERROR(-J16*$B$9+J16," ") -> 3.4127511 | L16: =IF(H16=$O$18,G16,IF(H16=O21,G16,IF(H16=O22,G16,IFERROR(IF(E16*K16/100<=$G$14,$G$14,E16*K16/100)," ")))) -> 15357380 | M16: =L16/$B$12 -> 1968.8949 | O16: TAJY FUERTE | P16: 8
A17: 4 | B17: IZUSU | C17: NQR71L | D17: 2018 | E17: 50000000 | F17: =E17/$B$12 -> 6410.2564 | G17: =VLOOKUP(H17,DATOS!$G$4:$H$12,2,0) -> 3190000 | H17: TAJY PREMIUM | I17: =IFERROR(VLOOKUP(H17,$O$14:$P$17,2,0)," ") -> 4 | J17: =IFERROR(VLOOKUP(E17,[1]Hoja1!$A$4:$J$354,I17,1)," ") -> 9.1259359 | K17: =IFERROR(-J17*$B$9+J17," ") -> 7.7570455 | L17: =IF(H17=$O$18,G17,IF(H17=O22,G17,IF(H17=O23,G17,IFERROR(IF(E17*K17/100<=$G$14,$G$14,E17*K17/100)," ")))) -> 3878522.7 | M17: =L17/$B$12 -> 497.24651 | O17: TAJY NOBLE | P17: 10
A18: 5 | B18: VOLKSWAGEN | C18: SAVEIRO | D18: 2021 | E18: 10000000 | F18: =E18/$B$12 -> 1282.0513 | G18: =VLOOKUP(H18,DATOS!$G$4:$H$12,2,0) -> 3190000 | H18: TAJY PREMIUM | I18: =IFERROR(VLOOKUP(H18,$O$14:$P$17,2,0)," ") -> 4 | J18: =IFERROR(VLOOKUP(E18,[1]Hoja1!$A$4:$J$354,I18,1)," ") -> 28.828119 | K18: =IFERROR(-J18*$B$9+J18," ") -> 24.503901 | L18: =IF(H18=$O$18,G18,IF(H18=O23,G18,IF(H18=O24,G18,IFERROR(IF(E18*K18/100<=$G$14,$G$14,E18*K18/100)," ")))) -> 3190000 | M18: =L18/$B$12 -> 408.97436 | N18: 600000 | O18: TAJY BASICO - AUTOMOVIL
A19: 6 | B19: SCANIA | C19: P94,260 | D19: 2001 | E19: 25000000 | F19: =E19/$B$12 -> 3205.1282 | G19: =VLOOKUP(H19,DATOS!$G$4:$H$12,2,0) -> 3190000 | H19: TAJY PREMIUM | I19: =IFERROR(VLOOKUP(H19,$O$14:$P$17,2,0)," ") -> 4 | J19: =IFERROR(VLOOKUP(E19,[1]Hoja1!$A$4:$J$354,I19,1)," ") -> 12.217879 | K19: =IFERROR(-J19*$B$9+J19," ") -> 10.385197 | L19: =IF(H19=$O$18,G19,IF(H19=O24,G19,IF(H19=O25,G19,IFERROR(IF(E19*K19/100<=$G$14,$G$14,E19*K19/100)," ")))) -> 3190000 | M19: =L19/$B$12 -> 408.97436 | N19: 1000000 | O19: TAJY BASICO - CAMION
A20: 7 | B20: MERCEDE BENZ | C20: GLC | D20: 2021 | E20: 35000000 | F20: =E20/$B$12 -> 4487.1795 | G20: =VLOOKUP(H20,DATOS!$G$4:$H$12,2,0) -> 3190000 | H20: TAJY PREMIUM | I20: =IFERROR(VLOOKUP(H20,$O$14:$P$17,2,0)," ") -> 4 | J20: =IFERROR(VLOOKUP(E20,[1]Hoja1!$A$4:$J$354,I20,1)," ") -> 10.094367 | K20: =IFERROR(-J20*$B$9+J20," ") -> 8.5802117 | L20: =IF(H20=$O$18,G20,IF(H20=O25,G20,IF(H20=O26,G20,IFERROR(IF(E20*K20/100<=$G$14,$G$14,E20*K20/100)," ")))) -> 3190000 | M20: =L20/$B$12 -> 408.97436 | N20: 800000 | O20: TAJY BASICO - ACOPLADO
A21: 8 | B21: FUSO | C21: FAV 1PH1L | D21: 2018 | E21: 45000000 | F21: =E21/$B$12 -> 5769.2308 | G21: =VLOOKUP(H21,DATOS!$G$4:$H$12,2,0) -> 3190000 | H21: TAJY PREMIUM | I21: =IFERROR(VLOOKUP(H21,$O$14:$P$17,2,0)," ") -> 4 | J21: =IFERROR(VLOOKUP(E21,[1]Hoja1!$A$4:$J$354,I21,1)," ") -> 9.6141517 | K21: =IFERROR(-J21*$B$9+J21," ") -> 8.1720289 | L21: =IF(H21=$O$18,G21,IF(H21=O26,G21,IF(H21=O27,G21,IFERROR(IF(E21*K21/100<=$G$14,$G$14,E21*K21/100)," ")))) -> 3677413 | M21: =L21/$B$12 -> 471.46321
A22: 9 | B22: TOYOTA | C22: HILUX | D22: 2008 | E22: 55000000 | F22: =E22/$B$12 -> 7051.2821 | G22: =VLOOKUP(H22,DATOS!$G$4:$H$12,2,0) -> 3190000 | H22: TAJY PREMIUM | I22: =IFERROR(VLOOKUP(H22,$O$14:$P$17,2,0)," ") -> 4 | J22: =IFERROR(VLOOKUP(E22,[1]Hoja1!$A$4:$J$354,I22,1)," ") -> 8.582883 | K22: =IFERROR(-J22*$B$9+J22," ") -> 7.2954505 | L22: =IF(H22=$O$18,G22,IF(H22=O27,G22,IF(H22=O28,G22,IFERROR(IF(E22*K22/100<=$G$14,$G$14,E22*K22/100)," ")))) -> 4012497.8 | M22: =L22/$B$12 -> 514.42279
A23: 10 | B23: TOYOTA | C23: HILUX | D23: 2008 | E23: 65000000 | F23: =E23/$B$12 -> 8333.3333 | G23: =VLOOKUP(H23,DATOS!$G$4:$H$12,2,0) -> 3190000 | H23: TAJY PREMIUM | I23: =IFERROR(VLOOKUP(H23,$O$14:$P$17,2,0)," ") -> 4 | J23: =IFERROR(VLOOKUP(E23,[1]Hoja1!$A$4:$J$354,I23,1)," ") -> 7.885038 | K23: =IFERROR(-J23*$B$9+J23," ") -> 6.7022823 | L23: =IF(H23=$O$18,G23,IF(H23=O28,G23,IF(H23=O29,G23,IFERROR(IF(E23*K23/100<=$G$14,$G$14,E23*K23/100)," ")))) -> 4356483.5 | M23: =L23/$B$12 -> 558.52352
A24: 11 | B24: TOYOTA | C24: HILUX | D24: 2008 | E24: 45000000 | F24: =E24/$B$12 -> 5769.2308 | G24: =VLOOKUP(H24,DATOS!$G$4:$H$12,2,0) -> 3190000 | H24: TAJY PREMIUM | I24: =IFERROR(VLOOKUP(H24,$O$14:$P$17,2,0)," ") -> 4 | J24: =IFERROR(VLOOKUP(E24,[1]Hoja1!$A$4:$J$354,I24,1)," ") -> 9.6141517 | K24: =IFERROR(-J24*$B$9+J24," ") -> 8.1720289 | L24: =IF(H24=$O$18,G24,IF(H24=O29,G24,IF(H24=O30,G24,IFERROR(IF(E24*K24/100<=$G$14,$G$14,E24*K24/100)," ")))) -> 3677413 | M24: =L24/$B$12 -> 471.46321
A25: 12 | B25: TOYOTA | C25: HILUX | D25: 2008 | E25: 60000000 | F25: =E25/$B$12 -> 7692.3077 | G25: =VLOOKUP(H25,DATOS!$G$4:$H$12,2,0) -> 3190000 | H25: TAJY PREMIUM | I25: =IFERROR(VLOOKUP(H25,$O$14:$P$17,2,0)," ") -> 4 | J25: =IFERROR(VLOOKUP(E25,[1]Hoja1!$A$4:$J$354,I25,1)," ") -> 8.1303389 | K25: =IFERROR(-J25*$B$9+J25," ") -> 6.9107881 | L25: =IF(H25=$O$18,G25,IF(H25=O30,G25,IF(H25=O31,G25,IFERROR(IF(E25*K25/100<=$G$14,$G$14,E25*K25/100)," ")))) -> 4146472.9 | M25: =L25/$B$12 -> 531.59908
A26: 13 | B26: TOYOTA | C26: HILUX | D26: 2008 | E26: 105000000 | F26: =E26/$B$12 -> 13461.538 | G26: =VLOOKUP(H26,DATOS!$G$4:$H$12,2,0) -> 3190000 | H26: TAJY PREMIUM | I26: =IFERROR(VLOOKUP(H26,$O$14:$P$17,2,0)," ") -> 4 | J26: =IFERROR(VLOOKUP(E26,[1]Hoja1!$A$4:$J$354,I26,1)," ") -> 6.036509 | K26: =IFERROR(-J26*$B$9+J26," ") -> 5.1310326 | L26: =IF(H26=$O$18,G26,IF(H26=O31,G26,IF(H26=O32,G26,IFERROR(IF(E26*K26/100<=$G$14,$G$14,E26*K26/100)," ")))) -> 5387584.3 | M26: =L26/$B$12 -> 690.71593
A27: 14 | B27: TOYOTA | C27: HILUX | D27: 2008 | E27: 105000000 | F27: =E27/$B$12 -> 13461.538 | G27: =VLOOKUP(H27,DATOS!$G$4:$H$12,2,0) -> 3190000 | H27: TAJY PREMIUM | I27: =IFERROR(VLOOKUP(H27,$O$14:$P$17,2,0)," ") -> 4 | J27: =IFERROR(VLOOKUP(E27,[1]Hoja1!$A$4:$J$354,I27,1)," ") -> 6.036509 | K27: =IFERROR(-J27*$B$9+J27," ") -> 5.1310326 | L27: =IF(H27=$O$18,G27,IF(H27=O32,G27,IF(H27=O33,G27,IFERROR(IF(E27*K27/100<=$G$14,$G$14,E27*K27/100)," ")))) -> 5387584.3 | M27: =L27/$B$12 -> 690.71593
A28: 15 | B28: TOYOTA | C28: HILUX | D28: 2008 | E28: 105000000 | F28: =E28/$B$12 -> 13461.538 | G28: =VLOOKUP(H28,DATOS!$G$4:$H$12,2,0) -> 3190000 | H28: TAJY PREMIUM | I28: =IFERROR(VLOOKUP(H28,$O$14:$P$17,2,0)," ") -> 4 | J28: =IFERROR(VLOOKUP(E28,[1]Hoja1!$A$4:$J$354,I28,1)," ") -> 6.036509 | K28: =IFERROR(-J28*$B$9+J28," ") -> 5.1310326 | L28: =IF(H28=$O$18,G28,IF(H28=O33,G28,IF(H28=O34,G28,IFERROR(IF(E28*K28/100<=$G$14,$G$14,E28*K28/100)," ")))) -> 5387584.3 | M28: =L28/$B$12 -> 690.71593
A29: 16 | B29: TOYOTA | C29: HILUX | D29: 2008 | E29: 105000000 | F29: =E29/$B$12 -> 13461.538 | G29: =VLOOKUP(H29,DATOS!$G$4:$H$12,2,0) -> 3190000 | H29: TAJY PREMIUM | I29: =IFERROR(VLOOKUP(H29,$O$14:$P$17,2,0)," ") -> 4 | J29: =IFERROR(VLOOKUP(E29,[1]Hoja1!$A$4:$J$354,I29,1)," ") -> 6.036509 | K29: =IFERROR(-J29*$B$9+J29," ") -> 5.1310326 | L29: =IF(H29=$O$18,G29,IF(H29=O34,G29,IF(H29=O35,G29,IFERROR(IF(E29*K29/100<=$G$14,$G$14,E29*K29/100)," ")))) -> 5387584.3 | M29: =L29/$B$12 -> 690.71593
A30: 17 | B30: HONDA | C30: CBF160 | D30: 2024 | E30: 105000000 | F30: =E30/$B$12 -> 13461.538 | G30: =VLOOKUP(H30,DATOS!$G$4:$H$12,2,0) -> 3190000 | H30: TAJY PREMIUM | I30: =IFERROR(VLOOKUP(H30,$O$14:$P$17,2,0)," ") -> 4 | J30: =IFERROR(VLOOKUP(E30,[1]Hoja1!$A$4:$J$354,I30,1)," ") -> 6.036509 | K30: =IFERROR(-J30*$B$9+J30," ") -> 5.1310326 | L30: =IF(H30=$O$18,G30,IF(H30=O35,G30,IF(H30=O36,G30,IFERROR(IF(E30*K30/100<=$G$14,$G$14,E30*K30/100)," ")))) -> 5387584.3 | M30: =L30/$B$12 -> 690.71593
D32: Suma total Gs. | E32: =SUM(E14:E30) -> 1665000000 | F32: =SUM(F14:F30) -> 213461.54 | L32: =SUM(L14:L30) -> 88072311 | M32: =SUM(M14:M30) -> 11291.322
D33: Costo Contado Gs. | E33: =ROUNDUP(L32,-3) -> 88073000 | F33: =E33/B12 -> 11291.41 | L33: =L32*1.1/12 -> 8073295.2 | M33: =M32*1.1/12 -> 1035.0378
D34: Costo financiado de Inicial y 11 Cuotas de Gs. | E34: =ROUNDUP(E33*1.1/12,-3) -> 8074000 | F34: =(F33*1.1/12) -> 1035.0459
